setup.py
server/__init__.py
server/server.py
server/common/__init__.py
server/common/meta.py
server/common/my_func.py
server/common/wrapper.py
server/log/__init__.py
server/log/client_log_config.py
server/log/server_log_config.py
server/log/wrapp_log_config.py
server/server/__init__.py
server/server/add_user.py
server/server/main_window.py
server/server/remove_user.py
server/server/server_d_b.py
server/server/server_oop.py
server/server/stat_window.py
server_proj_dav.egg-info/PKG-INFO
server_proj_dav.egg-info/SOURCES.txt
server_proj_dav.egg-info/dependency_links.txt
server_proj_dav.egg-info/requires.txt
server_proj_dav.egg-info/top_level.txt