Metadata-Version: 2.1
Name: server-proj-dav
Version: 0.0.2
Summary: Server packet
Home-page: UNKNOWN
Author: Konstantuan
Author-email: dakope@tut.by
License: UNKNOWN
Platform: UNKNOWN
